kalam/__init__.py
kalam/console.py
kalam-0.1.0.dist-info/entry_points.txt
kalam-0.1.0.dist-info/LICENSE
kalam-0.1.0.dist-info/WHEEL
kalam-0.1.0.dist-info/METADATA
kalam-0.1.0.dist-info/RECORD
